HowMonoPy/__init__.py
HowMonoPy/_wrapper.py
HowMonoPy/clib/howmonochromatic.dll
HowMonoPy/clib/libhowmonochromatic.so
HowMonoPy-0.3.dist-info/LICENSE
HowMonoPy-0.3.dist-info/METADATA
HowMonoPy-0.3.dist-info/WHEEL
HowMonoPy-0.3.dist-info/top_level.txt
HowMonoPy-0.3.dist-info/zip-safe
HowMonoPy-0.3.dist-info/RECORD
