Metadata-Version: 2.1
Name: HowMonoPy
Version: 0.3
Summary: A Python wrapper for the c library from how-monochromatic.
Home-page: https://github.com/SebTee/HowMonoPy
Author: Sebastian Tee
Maintainer: Sebastian Tee
License: MIT
Platform: Windows
Platform: Linux
Classifier: Operating System :: Microsoft :: Windows
Classifier: Operating System :: POSIX :: Linux
Classifier: Programming Language :: Python :: 3
Classifier: Programming Language :: Haskell
Classifier: Topic :: Scientific/Engineering :: Mathematics
Classifier: License :: OSI Approved :: MIT License
Classifier: Development Status :: 4 - Beta
License-File: LICENSE
